{
  "_page": {
    "output": "troupe/index.html",
    "template": "teatr/troupe"
  },
  "troupe": [
    [
      {
        "full_name": "Базилевич&nbsp;Богдан,&nbsp;член&nbsp;НСТДУ",
        "has_page": true,
        "image": {
          "name": "Базилевич&nbsp;Богдан,&nbsp;член&nbsp;НСТДУ",
          "url": "/korg/kol/portals/teatr/troup/bbazylevych/main_fh_gal_ix.jpg"
        },
        "url": "/troupe/bbazylevych/"
      },
      {
        "full_name": "Гелецький&nbsp;Володимир",
        "has_page": true,
        "image": {
          "name": "Гелецький&nbsp;Володимир",
          "url": "/korg/kol/portals/teatr/troup/vheletskyi/00_fh_gal_ix.jpg"
        },
        "url": "/troupe/vheletskyi/"
      }
    ],
    [
      {
        "full_name": "Глік&nbsp;Богдан",
        "has_page": true,
        "image": {
          "name": "Глік&nbsp;Богдан",
          "url": "/korg/kol/portals/teatr/troup/glikbogdan__gal_ix.jpg"
        },
        "url": "/troupe/glikbogdan/"
      },
      {
        "full_name": "Глушко&nbsp;Вячеслав",
        "has_page": true,
        "image": {
          "name": "Глушко&nbsp;Вячеслав",
          "url": "/korg/kol/portals/teatr/troup/glushko/glushko_main_fh_gal_ix.jpg"
        },
        "url": "/troupe/glushko/"
      }
    ],
    [
      {
        "full_name": "Катеринчук&nbsp;Марія",
        "has_page": true,
        "image": {
          "name": "Катеринчук&nbsp;Марія",
          "url": "/korg/kol/portals/teatr/troup/mkaterynchuk/main_fh_gal_ix.jpg"
        },
        "url": "/troupe/mkaterynchuk/"
      },
      {
        "full_name": "Комарова&nbsp;Надія, з.а. України,&nbsp;членкиня&nbsp;НСТДУ",
        "has_page": true,
        "image": {
          "name": "Комарова&nbsp;Надія, з.а. України,&nbsp;членкиня&nbsp;НСТДУ",
          "url": "/korg/kol/portals/teatr/troup/nkomarova/main_fh_gal_ix.jpg"
        },
        "url": "/troupe/nkomarova/"
      }
    ],
    [
      {
        "full_name": "Курко Оксана,&nbsp;членкиня&nbsp;НСТДУ",
        "has_page": true,
        "image": {
          "name": "Курко Оксана,&nbsp;членкиня&nbsp;НСТДУ",
          "url": "/korg/kol/portals/teatr/troup/okurko/main_fh_gal_ix.jpg"
        },
        "url": "/troupe/okurko/"
      },
      {
        "full_name": "Лаюк&nbsp;Арсен",
        "has_page": true,
        "image": {
          "name": "Лаюк&nbsp;Арсен",
          "url": "/korg/kol/portals/teatr/troup/layuk_arsen__gal_ix.jpeg"
        },
        "url": "/troupe/layukarsen/"
      }
    ],
    [
      {
        "full_name": "Лисенко&nbsp;Анна",
        "has_page": true,
        "image": {
          "name": "Лисенко&nbsp;Анна",
          "url": "/korg/kol/portals/teatr/troup/img_5563__gal_ix.jpeg"
        },
        "url": "/troupe/annalysenko/"
      },
      {
        "full_name": "Максимчук&nbsp;Іван",
        "has_page": true,
        "image": {
          "name": "Максимчук&nbsp;Іван",
          "url": "/korg/kol/portals/teatr/troup/maksymchuk_m/maksymchuk__gal_ix.jpg"
        },
        "url": "/troupe/maksymchuk_m/"
      }
    ],
    [
      {
        "full_name": "Мардарій&nbsp;Роман,&nbsp;член&nbsp;НСТДУ",
        "has_page": true,
        "image": {
          "name": "Мардарій&nbsp;Роман,&nbsp;член&nbsp;НСТДУ",
          "url": "/korg/kol/portals/teatr/troup/rmardariy/main_fh_gal_ix.jpg"
        },
        "url": "/troupe/rmardariy/"
      },
      {
        "full_name": "Мардарович&nbsp;Соломія",
        "has_page": true,
        "image": {
          "name": "Мардарович&nbsp;Соломія",
          "url": "/korg/kol/portals/teatr/troup/012_net__gal_ix.jpg"
        },
        "url": "/troupe/mardarovych/"
      }
    ],
    [
      {
        "full_name": "Моцок Любов,&nbsp;членкиня&nbsp;НСТДУ",
        "has_page": true,
        "image": {
          "name": "Моцок Любов,&nbsp;членкиня&nbsp;НСТДУ",
          "url": "/korg/kol/portals/teatr/troup/lmotsok/main_fh_gal_ix.jpg"
        },
        "url": "/troupe/lmotsok/"
      },
      {
        "full_name": "Новицький&nbsp;Захарій,&nbsp;член&nbsp;НСТДУ",
        "has_page": true,
        "image": {
          "name": "Новицький&nbsp;Захарій,&nbsp;член&nbsp;НСТДУ",
          "url": "/korg/kol/portals/teatr/troup/znovytskiy/main_fh_gal_ix.jpg"
        },
        "url": "/troupe/znovytskiy/"
      }
    ],
    [
      {
        "full_name": "Новосад&nbsp;Дмитро",
        "has_page": true,
        "image": {
          "name": "Новосад&nbsp;Дмитро",
          "url": "/korg/kol/portals/teatr/troup/novosad_d/novosad__gal_ix.jpg"
        },
        "url": "/troupe/novosad_d/"
      },
      {
        "full_name": "Первун&nbsp;Світлана",
        "has_page": true,
        "image": {
          "name": "Первун&nbsp;Світлана",
          "url": "/korg/kol/portals/teatr/troup/spervun/main_fh_gal_ix.jpg"
        },
        "url": "/troupe/spervun/"
      }
    ],
    [
      {
        "full_name": "Петрик&nbsp;Інна",
        "has_page": true,
        "image": {
          "name": "Петрик&nbsp;Інна",
          "url": "/korg/kol/portals/teatr/troup/petryk_i/petryk__gal_ix.jpg"
        },
        "url": "/troupe/petryk_i/"
      },
      {
        "full_name": "Сагалюк&nbsp;Катерина",
        "has_page": true,
        "image": {
          "name": "Сагалюк&nbsp;Катерина",
          "url": "/korg/kol/portals/teatr/troup/novyckak/novycka_main_fh_gal_ix.jpg"
        },
        "url": "/troupe/novyckak/"
      }
    ],
    [
      {
        "full_name": "Угорська-Геник Галина,&nbsp;членкиня&nbsp;НСТДУ",
        "has_page": true,
        "image": {
          "name": "Угорська-Геник Галина,&nbsp;членкиня&nbsp;НСТДУ",
          "url": "/korg/kol/portals/teatr/troup/huhorska/main_fh_gal_ix.jpg"
        },
        "url": "/troupe/huhorska/"
      },
      {
        "full_name": "Феняк&nbsp;Вікторія",
        "has_page": true,
        "image": {
          "name": "Феняк&nbsp;Вікторія",
          "url": "/korg/kol/portals/teatr/troup/вікторія_феняк_fh_gal_ix.jpg"
        },
        "url": "/troupe/185/"
      }
    ],
    [
      {
        "full_name": "Філімонов Артур,&nbsp;член&nbsp;НСТДУ",
        "has_page": true,
        "image": {
          "name": "Філімонов Артур,&nbsp;член&nbsp;НСТДУ",
          "url": "/korg/kol/portals/teatr/troup/filimonov/main__gal_ix.jpg"
        },
        "url": "/troupe/filimonov/"
      },
      {
        "full_name": "Філімонова Олександра,&nbsp;членкиня&nbsp;НСТДУ",
        "has_page": true,
        "image": {
          "name": "Філімонова Олександра,&nbsp;членкиня&nbsp;НСТДУ",
          "url": "/korg/kol/portals/teatr/troup/oskrygunec/main_fh_gal_ix.jpg"
        },
        "url": "/troupe/oskrygunec/"
      }
    ],
    [
      {
        "full_name": "Чиборак&nbsp;Уляна",
        "has_page": true,
        "image": {
          "name": "Чиборак&nbsp;Уляна",
          "url": "/korg/kol/portals/teatr/troup/uchuborak/main_fh_gal_ix.jpg"
        },
        "url": "/troupe/uchuborak/"
      },
      {
        "full_name": "Якубів Ольга,&nbsp;членкиня&nbsp;НСТДУ",
        "has_page": true,
        "image": {
          "name": "Якубів Ольга,&nbsp;членкиня&nbsp;НСТДУ",
          "url": "/korg/kol/portals/teatr/troup/ohnatiuk/iacubiv_main_1__gal_ix.jpg"
        },
        "url": "/troupe/ohnatiuk/"
      }
    ]
  ]
}