{
  "_page": {
    "output": "news/item/43685/firstpage.html",
    "template": "news/item"
  },
  "author": "",
  "body": "<p><em><img alt=\"\" class=\"l\" height=\"150\" src=\"/korg/kol/news/2012/43685/01_gallery.jpg\" title=\"Ігор ЮЗЮК, керівник літературно-драматургічної частини Коломийського театру\" width=\"200\"/><a href=\"http://teatr.kolomyya.org\" target=\"_blank\">Коломийський академічний обласний український драматичний театр імені Івана Озаркевича</a> продовжує гастрольне турне&nbsp;Україною.</em></p>\n<p>Цієї весни з мистецтвом театру після Івано-Франківська уже мали можливість познайомитися мешканці Кам’янця-Подільського. Попереду — Вінниця, Чернівці, Полтава, Кіровоград, Хмельницький і закордонний&nbsp;тур.</p>\n<p>Детальніше про гастролі та про тих, хто підтримує театральне мистецтво озарківчан, — керівник літературно-драматургічної частини театру Ігор&nbsp;Юзюк:</p>\n<p>\n<object data=\"http://odtrk.if.ua/wp-content/plugins/audio-player/player.swf\" height=\"24\" id=\"audioplayer1\" type=\"application/x-shockwave-flash\" width=\"290\">\n<param name=\"data\" value=\"http://odtrk.if.ua/wp-content/plugins/audio-player/player.swf\"/>\n<param name=\"FlashVars\" value=\"playerID=1&amp;bg=0xf8f8f8&amp;leftbg=0xeeeeee&amp;lefticon=0x666666&amp;rightbg=0xcccccc&amp;rightbghover=0x999999&amp;righticon=0x666666&amp;righticonhover=0xffffff&amp;text=0x666666&amp;slider=0x666666&amp;track=0xFFFFFF&amp;border=0x666666&amp;loader=0x9FFFB8&amp;soundFile=http%3A%2F%2Fodtrk.if.ua%2Fwp-content%2Fuploads%2F09%2F2011%2F01%2Fbfbe18b80a7c_9212%2F3f4915dd058f.mp3\"/>\n<param name=\"quality\" value=\"high\"/>\n<param name=\"menu\" value=\"false\"/>\n<param name=\"bgcolor\" value=\"#FFFFFF\"/>\n<param name=\"src\" value=\"http://odtrk.if.ua/wp-content/plugins/audio-player/player.swf\"/>\n</object>\n</p>",
  "caption": "Коломийський театр продовжує гастрольне турне&nbsp;Україною",
  "date": "14 березня 2012&nbsp;р.",
  "images": [],
  "keywords": null,
  "origin": "Івано-Франківська&nbsp;ОДТРК",
  "origin_url": "http://odtrk.if.ua"
}