{
  "_page": {
    "output": "news/item/57988/index.html",
    "template": "news/item"
  },
  "author": "",
  "body": "<p>11 різножанрових вистав, 10 академічних театрів, багато поважних діячів мистецтва – все це за шість днів. У столиці Покуття завершився Всеукраїнський театральний фестиваль сценічних першопрочитань &#8220;Коломийські представлення&#8221;. Останній акорд, як і минулого року, поставив Національний академічний драматичний театр імені Івана&nbsp;Франка.</p>\n<p style=\"text-align: center;\">\n<object data=\"//www.youtube.com/v/wMDVkhiGbp8?version=3&amp;hl=uk_UA\" height=\"480\" type=\"application/x-shockwave-flash\" width=\"640\">\n<param name=\"allowFullScreen\" value=\"true\"/>\n<param name=\"allowscriptaccess\" value=\"always\"/>\n<param name=\"src\" value=\"//www.youtube.com/v/wMDVkhiGbp8?version=3&amp;hl=uk_UA\"/>\n<param name=\"allowfullscreen\" value=\"true\"/>\n</object>\n</p>",
  "caption": "Коломийський театр&nbsp;відфестивалив",
  "date": "16 вересня 2014&nbsp;р.",
  "images": [],
  "keywords": null,
  "origin": "НТК",
  "origin_url": "ntktv.ua"
}