{
  "_page": {
    "output": "news/item/58450/firstpage.html",
    "template": "news/item"
  },
  "author": "",
  "body": "<p>❄️ Нам всім так хочеться дива&#8230; З початком зими приходить час добрих різдвяних вистав❄️<br/>Театр приймає замовлення!☃️Інформація і колективне бронювання за телефонами: 096 651 03 82, 099 198 57&nbsp;70</p>\n<p style=\"text-align: center;\"><img alt=\"\" class=\"l\" height=\"396\" src=\"/korg/kol/news/2023/58450/photo_5420401779167842197_x.jpg\" width=\"480\"/></p>",
  "caption": "❄️ Час добрих різдвяних&nbsp;вистав❄️",
  "date": "29 листопада 2023&nbsp;р.",
  "images": [],
  "keywords": null,
  "origin": "",
  "origin_url": null
}