{
  "_page": {
    "output": "news/year/2020/index.html",
    "template": "news/page"
  },
  "navigate_url": "/news/year/2020/pg/",
  "news": [
    {
      "date": "25 грудня 2020&nbsp;р.",
      "lead": "<p><img class=\"news_lead\" src=\"/korg/kol/news/2020/58424/teatr-241220_small_ix_crop.jpeg\"/>«Чудо святого Миколая». Актори Коломийського театру потішили&nbsp;прем&#8217;єрою&#8230;</p>",
      "title": "У Коломийському театрі прем'єра для дітей - «Чудо святого Миколая»",
      "url": "/news/item/58424"
    },
    {
      "date": "10 грудня 2020&nbsp;р.",
      "lead": "<p><img class=\"news_lead\" src=\"/korg/kol/news/2020/58423/21_small_ix_crop.jpg\"/>Засновник українського професійного театру, режисер, драматург і  актор Марко Кропивницький, 180-річчя від дня народження якого відзначається у 2020&nbsp;році&#8230;</p>",
      "title": "До 180-річчя з дня народження Марка Кропивницького. Рідкісна світлина батька українського театру",
      "url": "/news/item/58423"
    },
    {
      "date": "04 серпня 2020&nbsp;р.",
      "lead": "Коломийський академічний обласний український драматичний театр імені Озаркевича приступає до&nbsp;репетицій&#8230;",
      "title": "Відновлено проведення репетицій у Коломийському драмтеатрі (відеосюжет)",
      "url": "/news/item/58422"
    },
    {
      "date": "19 червня 2020&nbsp;р.",
      "lead": "Міністерство культури та інформаційної політики України відповідно до Указу Президента України «Про стипендії Президента України для молодих письменників і митців у сфері музичного, театрального,&nbsp;образотворчого",
      "title": "Проходить відбір кандидатів на здобуття стипендій Президента України для молодих письменників і митців",
      "url": "/news/item/58421"
    },
    {
      "date": "20 березня 2020&nbsp;р.",
      "lead": "24-26 липня 2020 року у місті НовоградІ - Волинському Житомирської області -\r\nна батьківщині великої української поетеси Лесі Українки&nbsp;відбудеться&#8230;",
      "title": "Увага! Конкурс!",
      "url": "/news/item/58420"
    }
  ],
  "page": 1,
  "pages": [
    1
  ],
  "pages_cnt": 1,
  "years": [
    {
      "next": false,
      "previous": false,
      "url": "/news/year/2026",
      "year": 2026
    },
    {
      "next": true,
      "previous": false,
      "url": "/news/year/2024",
      "year": 2024
    },
    {
      "next": false,
      "previous": false,
      "url": "/news/year/2023",
      "year": 2023
    },
    {
      "next": false,
      "previous": false,
      "url": "/news/year/2021",
      "year": 2021
    },
    {
      "next": false,
      "previous": false,
      "url": null,
      "year": 2020
    },
    {
      "next": false,
      "previous": false,
      "url": "/news/year/2019",
      "year": 2019
    },
    {
      "next": false,
      "previous": false,
      "url": "/news/year/2018",
      "year": 2018
    },
    {
      "next": false,
      "previous": true,
      "url": "/news/year/2017",
      "year": 2017
    },
    {
      "next": false,
      "previous": false,
      "url": "/news/year/2003",
      "year": 2003
    }
  ]
}