{
  "_page": {
    "output": "news/year/2021/pg/4/index.html",
    "template": "news/page"
  },
  "navigate_url": "/news/year/2021/pg/",
  "news": [
    {
      "date": "21 січня 2021&nbsp;р.",
      "lead": "Артистка театру Катерина Новицька стала стипендіаткою Президента України.&nbsp;Вітаємо!",
      "title": "Артистка театру Катерина Новицька стала стипендіаткою Президента України",
      "url": "/news/item/58425"
    }
  ],
  "page": 4,
  "pages": [
    1,
    2,
    3,
    4
  ],
  "pages_cnt": 4,
  "years": [
    {
      "next": false,
      "previous": false,
      "url": "/news/year/2024",
      "year": 2024
    },
    {
      "next": false,
      "previous": false,
      "url": null,
      "year": 2021
    },
    {
      "next": false,
      "previous": false,
      "url": "/news/year/2020",
      "year": 2020
    },
    {
      "next": false,
      "previous": false,
      "url": "/news/year/2019",
      "year": 2019
    },
    {
      "next": false,
      "previous": true,
      "url": "/news/year/2018",
      "year": 2018
    },
    {
      "next": false,
      "previous": false,
      "url": "/news/year/2003",
      "year": 2003
    }
  ]
}